<beans
	xmlns="http://www.springframework.org/schema/beans"
	xmlns:util="http://www.springframework.org/schema/util"
	xmlns:override="http://www.riotfamily.org/schema/common/override"
	xmlns:xsi="http://www.w3.org/2001/XMLSchema-instance"
	xsi:schemaLocation="
		http://www.springframework.org/schema/util
		http://www.springframework.org/schema/util/spring-util-2.0.xsd
		http://www.riotfamily.org/schema/common/override
		http://www.riotfamily.org/schema/common/override-7.0.xsd
		http://www.springframework.org/schema/beans
		http://www.springframework.org/schema/beans/spring-beans.xsd">

	<import resource="classpath:org/riotfamily/pages/runtime/db-schema.xml"/>
	
	<override:add ref="sessionFactory" property="mappingLocations">
		<value>classpath:org/riotfamily/pages/dao/hibernate/pages.hbm.xml</value>
	</override:add>

	<bean id="pageUrlBuilder" class="org.riotfamily.pages.mapping.PageUrlBuilder">
		<constructor-arg ref="pathCompleter" />
	</bean>
	
	<bean id="pageDao" class="org.riotfamily.pages.dao.hibernate.HibernatePageDao">
		<property name="componentDao" ref="componentDao" />
		<property name="sessionFactory" ref="sessionFactory" />
	</bean>

</beans>