<?xml version="1.0"?>
<!DOCTYPE hibernate-mapping PUBLIC
    "-//Hibernate/Hibernate Mapping DTD 3.0//EN"
    "http://hibernate.sourceforge.net/hibernate-mapping-3.0.dtd">


<hibernate-mapping package="org.riotfamily.components.model" auto-import="false">

	<class name="ComponentList" table="riot_component_lists">
		<cache usage="nonstrict-read-write" region="components" />
		<id name="id">
			<generator class="native" />
		</id>
		<list name="components" cascade="all">
			<cache usage="nonstrict-read-write" region="components" />
			<key column="list" />
			<index column="list_pos" />
			<one-to-many class="Component" />
		</list>
		<many-to-one name="container" cascade="save-update" />
	</class>

	<class name="ContentContainer" table="riot_content_containers" lazy="false" discriminator-value="ContentContainer">
		<cache usage="nonstrict-read-write" region="components" />
		<id name="id">
			<generator class="native" />
		</id>
		<discriminator column="container_type" type="string" />
		<many-to-one name="liveVersion" column="live_version" cascade="all" />
		<many-to-one name="previewVersion" column="preview_version" cascade="all" />
	</class>

	<class name="Content" table="riot_contents" lazy="false" discriminator-value="Content">
		<cache usage="nonstrict-read-write" region="components" />
		<id name="id">
			<generator class="native" />
		</id>
		<discriminator column="content_type" type="string" />
		<property name="dirty" />
		<map name="wrappers" table="riot_content_values" cascade="all-delete-orphan" lazy="false">
			<cache usage="nonstrict-read-write" region="components" />
			<key column="content" />
			<index column="property" type="string" />
			<many-to-many column="wrapper" class="org.riotfamily.components.model.wrapper.ValueWrapper" />
		</map>
		<subclass name="Component" discriminator-value="Component">
			<property name="type" column="component_type" />
			<many-to-one name="list" column="list" insert="false" update="false" access="field" />
		</subclass>
	</class>
	
</hibernate-mapping>
